<annotation>
	<folder>parked bikes on sidewalk - Google Search</folder>
	<filename>Bicycle Facilities _ City of Winston.jpg</filename>
	<path>/Users/shiii266/Downloads/parked bikes on sidewalk - Google Search/Bicycle Facilities _ City of Winston.jpg</path>
	<source>
		<database>Unknown</database>
	</source>
	<size>
		<width>2600</width>
		<height>1685</height>
		<depth>3</depth>
	</size>
	<segmented>0</segmented>
	<object>
		<name>bike</name>
		<pose>Unspecified</pose>
		<truncated>0</truncated>
		<difficult>0</difficult>
		<bndbox>
			<xmin>380</xmin>
			<ymin>529</ymin>
			<xmax>1461</xmax>
			<ymax>1615</ymax>
		</bndbox>
	</object>
</annotation>
